describealign.py
describealign-2.0.2.dist-info/licenses/LICENSE
describealign-2.0.2.dist-info/METADATA
describealign-2.0.2.dist-info/WHEEL
describealign-2.0.2.dist-info/entry_points.txt
describealign-2.0.2.dist-info/top_level.txt
describealign-2.0.2.dist-info/RECORD
