Metadata-Version: 2.4
Name: describealign
Version: 2.0.2
Summary: Combines videos with matching audio files (e.g. audio descriptions)
Author-email: Julian Brown <julbean@proton.me>
License-Expression: GPL-3.0-only
Project-URL: Homepage, https://github.com/julbean/describealign
Project-URL: Bug Tracker, https://github.com/julbean/describealign/issues
Keywords: audio,description,alignment,describe,align,video,media,stretch,time-scale,match,combine,fit,blind,impaired,track,sync,synchronize,register,accessible,accessibility,descriptive,narration,visual,low-vision,disability,access,assistive
Classifier: Programming Language :: Python :: 3
Classifier: Operating System :: OS Independent
Requires-Python: >=3.8
License-File: LICENSE
Requires-Dist: ffmpeg_python~=0.2.0
Requires-Dist: static-ffmpeg~=2.5
Requires-Dist: matplotlib~=3.9
Requires-Dist: numpy<3.0,>=1.21
Requires-Dist: scipy~=1.10
Requires-Dist: platformdirs~=4.2
Requires-Dist: natsort~=8.4.0
Requires-Dist: wxPython~=4.2.3
Requires-Dist: sortedcontainers~=2.4.0
Dynamic: license-file
